srecli/__init__.py
srecli/cli.py
srecli/commands/__init__.py
srecli/commands/cmd_status.py
srecli/options/__init__.py
srecli/options/common.py
srecli-0.0.7.dist-info/LICENSE
srecli-0.0.7.dist-info/METADATA
srecli-0.0.7.dist-info/WHEEL
srecli-0.0.7.dist-info/entry_points.txt
srecli-0.0.7.dist-info/top_level.txt
srecli-0.0.7.dist-info/RECORD
