Metadata-Version: 2.1
Name: srecli
Version: 0.0.7
Summary: srecli is a click based CLI tool to cater common SRE related system automation tasks.
Author-email: Shibhikkiran D <shibhikkiran@example.com>
Classifier: Programming Language :: Python :: 3
Classifier: License :: OSI Approved :: MIT License
Classifier: Operating System :: OS Independent
Requires-Python: >=3.7
License-File: LICENSE
Requires-Dist: click (~=8.1.3)
Requires-Dist: loguru (~=0.7.0)
Provides-Extra: ci
Requires-Dist: pylint (~=2.14.0) ; extra == 'ci'
Requires-Dist: toml (~=0.10.2) ; extra == 'ci'
Requires-Dist: yapf (~=0.32.0) ; extra == 'ci'
Requires-Dist: black (~=23.3.0) ; extra == 'ci'
Requires-Dist: pytest-cov[all] (~=3.0.0) ; extra == 'ci'
Requires-Dist: pytest (<5.0.0) ; extra == 'ci'
Requires-Dist: tox (~=4.5.2) ; extra == 'ci'
Provides-Extra: dev
Requires-Dist: pylint (~=2.14.0) ; extra == 'dev'
Requires-Dist: toml (~=0.10.2) ; extra == 'dev'
Requires-Dist: yapf (~=0.32.0) ; extra == 'dev'
Requires-Dist: black (~=23.3.0) ; extra == 'dev'
Provides-Extra: test
Requires-Dist: pytest-cov (~=4.1.0) ; extra == 'test'
Requires-Dist: pytest (~=7.3.1) ; extra == 'test'
